big_o/__init__.py
big_o/big_o.py
big_o/complexities.py
big_o/datagen.py
big_o/test/__init__.py
big_o/test/test_big_o.py
big_o/test/test_complexities.py
big_O_dmunguiatec-0.0.1.dist-info/LICENSE.txt
big_O_dmunguiatec-0.0.1.dist-info/METADATA
big_O_dmunguiatec-0.0.1.dist-info/WHEEL
big_O_dmunguiatec-0.0.1.dist-info/top_level.txt
big_O_dmunguiatec-0.0.1.dist-info/RECORD
