Metadata-Version: 2.1
Name: big-O-dmunguiatec
Version: 0.0.1
Summary: Empirical estimation of time complexity from execution time
Home-page: https://github.com/pberkes/big_O
Author: Pietro Berkes
Author-email: pietro.berkes@googlemail.com
License: LICENSE.txt
Platform: UNKNOWN
Requires-Dist: numpy
